gimpysolver
